pytrie/__init__.py
pytrie/__main__.py
tests/__init__.py
tests/test.py
py_trie-1.0.0.dist-info/METADATA
py_trie-1.0.0.dist-info/WHEEL
py_trie-1.0.0.dist-info/entry_points.txt
py_trie-1.0.0.dist-info/top_level.txt
py_trie-1.0.0.dist-info/RECORD
