Metadata-Version: 2.1
Name: py-trie
Version: 1.0.0
Summary: CLI for communicating with a Trie hosted online
Home-page: https://github.com/ayush055/trie-project
Author: Ayush Agarwal
Author-email: ayushagarwal2500@gmail.com
License: MIT
Platform: UNKNOWN
Classifier: License :: OSI Approved :: MIT License
Classifier: Programming Language :: Python :: 3
Classifier: Programming Language :: Python :: 3.8
Requires-Dist: click
